{
  "formatVersion": 1,
  "database": {
    "version": 1,
    "identityHash": "013621035a43f08778b6ab67696e122a",
    "entities": [
      {
        "tableName": "movies",
        "createSql": "CREATE TABLE IF NOT EXISTS `${TABLE_NAME}` (`_id` INTEGER PRIMARY KEY AUTOINCREMENT NOT NULL, `id` INTEGER NOT NULL, `title` TEXT, `body` TEXT, `uri` TEXT, `rating` INTEGER NOT NULL, `watched` INTEGER NOT NULL, `category` TEXT)",
        "fields": [
          {
            "fieldPath": "_id",
            "columnName": "_id",
            "affinity": "INTEGER",
            "notNull": true
          },
          {
            "fieldPath": "webId",
            "columnName": "id",
            "affinity": "INTEGER",
            "notNull": true
          },
          {
            "fieldPath": "title",
            "columnName": "title",
            "affinity": "TEXT",
            "notNull": false
          },
          {
            "fieldPath": "body",
            "columnName": "body",
            "affinity": "TEXT",
            "notNull": false
          },
          {
            "fieldPath": "uri",
            "columnName": "uri",
            "affinity": "TEXT",
            "notNull": false
          },
          {
            "fieldPath": "rating",
            "columnName": "rating",
            "affinity": "INTEGER",
            "notNull": true
          },
          {
            "fieldPath": "watched",
            "columnName": "watched",
            "affinity": "INTEGER",
            "notNull": true
          },
          {
            "fieldPath": "category",
            "columnName": "category",
            "affinity": "TEXT",
            "notNull": false
          }
        ],
        "primaryKey": {
          "columnNames": [
            "_id"
          ],
          "autoGenerate": true
        },
        "indices": [],
        "foreignKeys": []
      }
    ],
    "setupQueries": [
      "CREATE TABLE IF NOT EXISTS room_master_table (id INTEGER PRIMARY KEY,identity_hash TEXT)",
      "INSERT OR REPLACE INTO room_master_table (id,identity_hash) VALUES(42, \"013621035a43f08778b6ab67696e122a\")"
    ]
  }
}